test_py_abc/__init__.py
test_py_abc/convery_jax_pt.py
test-0.0.3.dist-info/LICENSE
test-0.0.3.dist-info/METADATA
test-0.0.3.dist-info/WHEEL
test-0.0.3.dist-info/top_level.txt
test-0.0.3.dist-info/RECORD
