Metadata-Version: 2.1
Name: test
Version: 0.0.3
Summary: Test for PyPI!
Author-email: test <test@example.com>
Project-URL: Repository, https://github.com/yixiaoer/test
Project-URL: Issues, https://github.com/yixiaoer/test/issues
Classifier: Development Status :: 4 - Beta
Classifier: Programming Language :: Python
Classifier: License :: OSI Approved :: MIT License
Requires-Python: >=3.8
License-File: LICENSE
Requires-Dist: mypy
Requires-Dist: jax
Requires-Dist: torch
Requires-Dist: transformers
Requires-Dist: einops
